pyautomator/__init__.py
pyautomator/cli.py
pyautomator-0.0.0.dist-info/METADATA
pyautomator-0.0.0.dist-info/WHEEL
pyautomator-0.0.0.dist-info/entry_points.txt
pyautomator-0.0.0.dist-info/RECORD
