Metadata-Version: 2.1
Name: pyautomator
Version: 0.0.0
Summary: A Python package that reticulates splines.
Home-page: https://github.com/seanchatmangpt/pyautomator
Author: Sean Chatmanm
Author-email: info@chatmangpt.com
Requires-Python: >=3.12,<4.0
Classifier: Programming Language :: Python :: 3
Classifier: Programming Language :: Python :: 3.12
Requires-Dist: typer[all] (>=0.12.0)
Project-URL: Repository, https://github.com/seanchatmangpt/pyautomator
